{"kind":"Article","sha256":"4ec9790f1bcd8948561aa0ef730cdb4d489600bf4de50d1df68e0258bcf7a13c","slug":"sds","location":"/03. sds.md","dependencies":[],"frontmatter":{"title":"Software Design Specification","short_title":"Software Design Specification","subtitle":"Key Transfer System","github":"https://github.com/flower4e/key-transfer-myst.git","keywords":["3DS","security","acquiring"],"authors":[{"nameParsed":{"literal":"Tsvetelina Georgieva","given":"Tsvetelina","family":"Georgieva"},"name":"Tsvetelina Georgieva","email":"cgeorgieva@datamax.bg","roles":["Writing – original draft","Writing – review & editing","Visualization"],"id":"contributors-Users\\flowe\\Desktop\\Key Transfer System\\03- sds-generated-uid-0","corresponding":true}],"date":"2023-03-24T00:00:00.000Z","license":{"content":{"id":"Apache-2.0","name":"Apache License 2.0","osi":true,"free":true,"url":"https://opensource.org/licenses/Apache-2.0"}},"subject":"DataMax Project","exports":[{"format":"md","filename":"03. sds.md","url":"/03. sds-9e7ed57130eb8a9cd56627ad17ddd63d.md"}]},"mdast":{"type":"root","children":[{"type":"block","children":[{"type":"heading","depth":2,"position":{"start":{"line":24,"column":1},"end":{"line":24,"column":1}},"children":[{"type":"text","value":"Използвани термини","position":{"start":{"line":24,"column":1},"end":{"line":24,"column":1}},"key":"MR1HDqmUMg"}],"identifier":"id","label":"Използвани термини","html_id":"id","implicit":true,"key":"ygUCR2z5rm"},{"type":"table","position":{"start":{"line":26,"column":1},"end":{"line":33,"column":1}},"children":[{"type":"tableRow","position":{"start":{"line":26,"column":1},"end":{"line":26,"column":1}},"children":[{"type":"tableCell","header":true,"position":{"start":{"line":26,"column":1},"end":{"line":26,"column":1}},"children":[{"type":"text","value":"Термин","position":{"start":{"line":26,"column":1},"end":{"line":26,"column":1}},"key":"SLbjbnU0kj"}],"key":"FbWvdHS2Zn"},{"type":"tableCell","header":true,"position":{"start":{"line":26,"column":1},"end":{"line":26,"column":1}},"children":[{"type":"text","value":"Описание","position":{"start":{"line":26,"column":1},"end":{"line":26,"column":1}},"key":"JcdRUPUS81"}],"key":"motSW33NwH"}],"key":"p4OEvUNrVK"},{"type":"tableRow","position":{"start":{"line":28,"column":1},"end":{"line":28,"column":1}},"children":[{"type":"tableCell","position":{"start":{"line":28,"column":1},"end":{"line":28,"column":1}},"children":[{"type":"strong","position":{"start":{"line":28,"column":1},"end":{"line":28,"column":1}},"children":[{"type":"text","value":"Криптографскa смарт картa","position":{"start":{"line":28,"column":1},"end":{"line":28,"column":1}},"key":"wDe4UxDWR7"}],"key":"oNiYN24l4w"}],"key":"AHjz6MiQt6"},{"type":"tableCell","position":{"start":{"line":28,"column":1},"end":{"line":28,"column":1}},"children":[{"type":"text","value":"Специализиран криптографски хардуер, който позволява да се използват  алгоритми като RSA и DSA; позволява да се генерира двойка секретни ключове на самата карта.","position":{"start":{"line":28,"column":1},"end":{"line":28,"column":1}},"key":"vsQBQE5E39"}],"key":"xqD1tHB4Js"}],"key":"GTcsiqqLZV"},{"type":"tableRow","position":{"start":{"line":29,"column":1},"end":{"line":29,"column":1}},"children":[{"type":"tableCell","position":{"start":{"line":29,"column":1},"end":{"line":29,"column":1}},"children":[{"type":"strong","position":{"start":{"line":29,"column":1},"end":{"line":29,"column":1}},"children":[{"type":"text","value":"Key Transfer Utility","position":{"start":{"line":29,"column":1},"end":{"line":29,"column":1}},"key":"NlzHepR4Jf"}],"key":"YAJTRqBTjd"}],"key":"V7BScEXpm2"},{"type":"tableCell","position":{"start":{"line":29,"column":1},"end":{"line":29,"column":1}},"children":[{"type":"text","value":"Мобилно приложение, което има роля на криптографскa смарт картa. Разработено е с цел пренос на данни на криптографски ключове.","position":{"start":{"line":29,"column":1},"end":{"line":29,"column":1}},"key":"F1LEY7W8Yv"}],"key":"aC6z1Ci4re"}],"key":"vqfoAorwoJ"},{"type":"tableRow","position":{"start":{"line":30,"column":1},"end":{"line":30,"column":1}},"children":[{"type":"tableCell","position":{"start":{"line":30,"column":1},"end":{"line":30,"column":1}},"children":[{"type":"strong","position":{"start":{"line":30,"column":1},"end":{"line":30,"column":1}},"children":[{"type":"text","value":"Картов четец","position":{"start":{"line":30,"column":1},"end":{"line":30,"column":1}},"key":"PuAUAKVYhU"}],"key":"W8WA6CH1a7"}],"key":"mvvczThZmn"},{"type":"tableCell","position":{"start":{"line":30,"column":1},"end":{"line":30,"column":1}},"children":[{"type":"text","value":"Устройство, което предава данни на криптографскa смарт карта чрез безконтактна технология","position":{"start":{"line":30,"column":1},"end":{"line":30,"column":1}},"key":"bgJjadC2mN"}],"key":"edb0FW6oEk"}],"key":"HceWKOHoKt"},{"type":"tableRow","position":{"start":{"line":31,"column":1},"end":{"line":31,"column":1}},"children":[{"type":"tableCell","position":{"start":{"line":31,"column":1},"end":{"line":31,"column":1}},"children":[{"type":"strong","position":{"start":{"line":31,"column":1},"end":{"line":31,"column":1}},"children":[{"type":"text","value":"APDU","position":{"start":{"line":31,"column":1},"end":{"line":31,"column":1}},"key":"cRsbPlcoMI"}],"key":"ufSilILJFX"}],"key":"AueHuK8BYO"},{"type":"tableCell","position":{"start":{"line":31,"column":1},"end":{"line":31,"column":1}},"children":[{"type":"text","value":"Application Protocol Data Units - Команди, които четецът изпраща на смарт картата и съответно чете отговорите от нея","position":{"start":{"line":31,"column":1},"end":{"line":31,"column":1}},"key":"hVrkQTN6Ug"}],"key":"frA5Mrrw4c"}],"key":"HG1t3N0qdB"},{"type":"tableRow","position":{"start":{"line":32,"column":1},"end":{"line":32,"column":1}},"children":[{"type":"tableCell","position":{"start":{"line":32,"column":1},"end":{"line":32,"column":1}},"children":[{"type":"strong","position":{"start":{"line":32,"column":1},"end":{"line":32,"column":1}},"children":[{"type":"text","value":"BDK","position":{"start":{"line":32,"column":1},"end":{"line":32,"column":1}},"key":"eBixK47i1o"}],"key":"I862xoI3hF"}],"key":"beDhFsUhUq"},{"type":"tableCell","position":{"start":{"line":32,"column":1},"end":{"line":32,"column":1}},"children":[{"type":"text","value":"Base Derivation Key - Основен ключ за извличане. BDK случайно генериран и с негова помощ се  извеждат всички ключове на терминали","position":{"start":{"line":32,"column":1},"end":{"line":32,"column":1}},"key":"SnfHLECSsq"}],"key":"kujWItAwra"}],"key":"awFcq7rnGq"},{"type":"tableRow","position":{"start":{"line":33,"column":1},"end":{"line":33,"column":1}},"children":[{"type":"tableCell","position":{"start":{"line":33,"column":1},"end":{"line":33,"column":1}},"children":[{"type":"strong","position":{"start":{"line":33,"column":1},"end":{"line":33,"column":1}},"children":[{"type":"text","value":"HSM","position":{"start":{"line":33,"column":1},"end":{"line":33,"column":1}},"key":"lu3fuklRSw"}],"key":"zvSQjDk2tx"}],"key":"HNFIYoaMBl"},{"type":"tableCell","position":{"start":{"line":33,"column":1},"end":{"line":33,"column":1}},"children":[{"type":"text","value":"Hardware Security Module - Модул за хардуерна сигурност – физическо изчислително устройство, което защитава и управлява цифрови ключове, изпълнява функции за криптиране и декриптиране за цифрови  подписи, силно удостоверяване и други криптографски функции","position":{"start":{"line":33,"column":1},"end":{"line":33,"column":1}},"key":"IwEDp9T4dH"}],"key":"OIM9uVnIum"}],"key":"MptLCw1aHG"}],"key":"mjgf2fejhu"},{"type":"heading","depth":2,"position":{"start":{"line":35,"column":1},"end":{"line":35,"column":1}},"children":[{"type":"text","value":"Въведение","position":{"start":{"line":35,"column":1},"end":{"line":35,"column":1}},"key":"iIXxdl80f4"}],"identifier":"id","label":"Въведение","html_id":"id-1","implicit":true,"key":"axM1h5CmQC"},{"type":"paragraph","position":{"start":{"line":37,"column":1},"end":{"line":37,"column":1}},"children":[{"type":"text","value":"Този документ съдържа подробно описание на софтуерната архитектура и дизайн на Система за пренос на криптографски данни, чрез която се осъществява пренос на криптографски ключове и техните данни между отделни устройства и карти. Документът има за цел да улови и предаде значимите архитектурни и дизайнерски решения и да покаже как дизайнът ще изпълни функционалните и нефункционалните изисквания, описани в документ System Requirements Specification.","position":{"start":{"line":37,"column":1},"end":{"line":37,"column":1}},"key":"jQ0ze7u5n7"}],"key":"w02UfNV3MO"},{"type":"heading","depth":2,"position":{"start":{"line":39,"column":1},"end":{"line":39,"column":1}},"children":[{"type":"text","value":"Система за пренос на криптографски данни","position":{"start":{"line":39,"column":1},"end":{"line":39,"column":1}},"key":"DPfpsWH3wD"}],"identifier":"id","label":"Система за пренос на криптографски данни","html_id":"id-2","implicit":true,"key":"SRVW5Kjim9"},{"type":"paragraph","position":{"start":{"line":41,"column":1},"end":{"line":41,"column":1}},"children":[{"type":"text","value":"В Система за пренос на криптографски данни се осъществява пренос данни на криптографски ключове. Обменът се извършва между картов четец - криптографска смарт карта - терминал, в съответствие PCI Security Standard, както и с останалите международно приети норми, разпоредби и стандарти за сигурност.","position":{"start":{"line":41,"column":1},"end":{"line":41,"column":1}},"key":"xQnUy5FGGa"}],"key":"SBPNo69zU7"},{"type":"heading","depth":2,"position":{"start":{"line":43,"column":1},"end":{"line":43,"column":1}},"children":[{"type":"text","value":"Участници","position":{"start":{"line":43,"column":1},"end":{"line":43,"column":1}},"key":"lG6Jo8xRAP"}],"identifier":"id","label":"Участници","html_id":"id-3","implicit":true,"key":"zHg0rvqiuT"},{"type":"paragraph","position":{"start":{"line":45,"column":1},"end":{"line":45,"column":1}},"children":[{"type":"text","value":"Участниците и компонентите в процеса на пренос на данни на криптографски ключове са следните:","position":{"start":{"line":45,"column":1},"end":{"line":45,"column":1}},"key":"Atmz2uWIKv"}],"key":"T9HkEqJF6z"},{"type":"list","ordered":false,"spread":false,"position":{"start":{"line":47,"column":1},"end":{"line":62,"column":1}},"children":[{"type":"listItem","spread":true,"position":{"start":{"line":47,"column":1},"end":{"line":54,"column":1}},"children":[{"type":"paragraph","position":{"start":{"line":47,"column":1},"end":{"line":47,"column":1}},"children":[{"type":"text","value":"Hardware","position":{"start":{"line":47,"column":1},"end":{"line":47,"column":1}},"key":"u6K2pkvkzw"}],"key":"pCB8JhksEe"},{"type":"list","ordered":false,"spread":false,"position":{"start":{"line":48,"column":1},"end":{"line":54,"column":1}},"children":[{"type":"listItem","spread":true,"position":{"start":{"line":48,"column":1},"end":{"line":48,"column":1}},"children":[{"type":"crossReference","position":{"start":{"line":48,"column":1},"end":{"line":48,"column":1}},"children":[{"type":"text","value":"Terminal Key Distribution Station","position":{"start":{"line":48,"column":1},"end":{"line":48,"column":1}},"key":"zPXyDNX8L8"}],"urlSource":"#tkd1","identifier":"tkd1","label":"tkd1","kind":"heading","template":"{name}","resolved":true,"html_id":"tkd1","key":"DJ0X7b7QB7"}],"key":"Re0SyaOdP1"},{"type":"listItem","spread":true,"position":{"start":{"line":49,"column":1},"end":{"line":49,"column":1}},"children":[{"type":"crossReference","position":{"start":{"line":49,"column":1},"end":{"line":49,"column":1}},"children":[{"type":"text","value":"HSM","position":{"start":{"line":49,"column":1},"end":{"line":49,"column":1}},"key":"SOAmwgkKXt"}],"urlSource":"#hsm1","identifier":"hsm1","label":"hsm1","kind":"heading","template":"{name}","resolved":true,"html_id":"hsm1","key":"SST13qbsUn"}],"key":"jteMWzlcv4"},{"type":"listItem","spread":true,"position":{"start":{"line":50,"column":1},"end":{"line":50,"column":1}},"children":[{"type":"crossReference","position":{"start":{"line":50,"column":1},"end":{"line":50,"column":1}},"children":[{"type":"text","value":"Картов четец","position":{"start":{"line":50,"column":1},"end":{"line":50,"column":1}},"key":"jKMI8woSjL"}],"urlSource":"#reader1","identifier":"reader1","label":"reader1","kind":"heading","template":"{name}","resolved":true,"html_id":"reader1","key":"ZUO1LjAFXV"}],"key":"CD8krfR7qu"},{"type":"listItem","spread":true,"position":{"start":{"line":51,"column":1},"end":{"line":51,"column":1}},"children":[{"type":"crossReference","position":{"start":{"line":51,"column":1},"end":{"line":51,"column":1}},"children":[{"type":"text","value":"Терминал","position":{"start":{"line":51,"column":1},"end":{"line":51,"column":1}},"key":"EK4M2FxHdJ"}],"urlSource":"#terminal1","identifier":"terminal1","label":"terminal1","kind":"heading","template":"{name}","resolved":true,"html_id":"terminal1","key":"tTkXDNJEW9"}],"key":"lIMkAahMQV"},{"type":"listItem","spread":true,"position":{"start":{"line":52,"column":1},"end":{"line":52,"column":1}},"children":[{"type":"crossReference","position":{"start":{"line":52,"column":1},"end":{"line":52,"column":1}},"children":[{"type":"text","value":"Мобилно устройство_1","position":{"start":{"line":52,"column":1},"end":{"line":52,"column":1}},"key":"zIrpeELvow"}],"urlSource":"#device1","identifier":"device1","label":"device1","kind":"heading","template":"{name}","resolved":true,"html_id":"device1","key":"agxARNsONM"}],"key":"NCZXXEwlNa"},{"type":"listItem","spread":true,"position":{"start":{"line":53,"column":1},"end":{"line":54,"column":1}},"children":[{"type":"crossReference","position":{"start":{"line":53,"column":1},"end":{"line":53,"column":1}},"children":[{"type":"text","value":"Мобилно устройство_2","position":{"start":{"line":53,"column":1},"end":{"line":53,"column":1}},"key":"gE6MRuHH5s"}],"urlSource":"#device1","identifier":"device1","label":"device1","kind":"heading","template":"{name}","resolved":true,"html_id":"device1","key":"ipxQY8oRbG"}],"key":"Wto3Avw8ij"}],"key":"mBFlUoOdKd"}],"key":"WWub0JrWes"},{"type":"listItem","spread":true,"position":{"start":{"line":55,"column":1},"end":{"line":62,"column":1}},"children":[{"type":"paragraph","position":{"start":{"line":55,"column":1},"end":{"line":55,"column":1}},"children":[{"type":"text","value":"Software","position":{"start":{"line":55,"column":1},"end":{"line":55,"column":1}},"key":"Chmpd9GIJW"}],"key":"KiFZmQw5dp"},{"type":"list","ordered":false,"spread":false,"position":{"start":{"line":56,"column":1},"end":{"line":62,"column":1}},"children":[{"type":"listItem","spread":true,"position":{"start":{"line":56,"column":1},"end":{"line":56,"column":1}},"children":[{"type":"crossReference","position":{"start":{"line":56,"column":1},"end":{"line":56,"column":1}},"children":[{"type":"text","value":"Linux","position":{"start":{"line":56,"column":1},"end":{"line":56,"column":1}},"key":"peePtvg1lB"}],"urlSource":"#linux1","identifier":"linux1","label":"linux1","kind":"heading","template":"{name}","resolved":true,"html_id":"linux1","key":"u0mSohoj4X"}],"key":"WVBZA4dA8L"},{"type":"listItem","spread":true,"position":{"start":{"line":57,"column":1},"end":{"line":57,"column":1}},"children":[{"type":"text","value":"Android OS","position":{"start":{"line":57,"column":1},"end":{"line":57,"column":1}},"key":"gHt0mIcDZ6"}],"key":"rYCLaUbww9"},{"type":"listItem","spread":true,"position":{"start":{"line":58,"column":1},"end":{"line":58,"column":1}},"children":[{"type":"crossReference","position":{"start":{"line":58,"column":1},"end":{"line":58,"column":1}},"children":[{"type":"text","value":"Key Transfer Utility","position":{"start":{"line":58,"column":1},"end":{"line":58,"column":1}},"key":"W1YFOOm0YR"}],"urlSource":"#utility1","identifier":"utility1","label":"utility1","kind":"heading","template":"{name}","resolved":true,"html_id":"utility1","key":"fp4VeDm5Fs"}],"key":"PDKRaA1fM3"},{"type":"listItem","spread":true,"position":{"start":{"line":59,"column":1},"end":{"line":59,"column":1}},"children":[{"type":"crossReference","position":{"start":{"line":59,"column":1},"end":{"line":59,"column":1}},"children":[{"type":"text","value":"Terminal-kdc","position":{"start":{"line":59,"column":1},"end":{"line":59,"column":1}},"key":"oloyCgGjqa"}],"urlSource":"#kdc1","identifier":"kdc1","label":"kdc1","kind":"heading","template":"{name}","resolved":true,"html_id":"kdc1","key":"lUP4do4gXV"}],"key":"F9Q1P9F4To"},{"type":"listItem","spread":true,"position":{"start":{"line":60,"column":1},"end":{"line":60,"column":1}},"children":[{"type":"crossReference","position":{"start":{"line":60,"column":1},"end":{"line":60,"column":1}},"children":[{"type":"text","value":"BDK","position":{"start":{"line":60,"column":1},"end":{"line":60,"column":1}},"key":"T1UCGdQmX8"}],"urlSource":"#bdk1","identifier":"bdk1","label":"bdk1","kind":"heading","template":"{name}","resolved":true,"html_id":"bdk1","key":"uUOfoXTH06"}],"key":"pJUTbkzxbj"},{"type":"listItem","spread":true,"position":{"start":{"line":61,"column":1},"end":{"line":62,"column":1}},"children":[{"type":"crossReference","position":{"start":{"line":61,"column":1},"end":{"line":61,"column":1}},"children":[{"type":"text","value":"APDU","position":{"start":{"line":61,"column":1},"end":{"line":61,"column":1}},"key":"Q660C0RXd4"}],"urlSource":"#apdu1","identifier":"apdu1","label":"apdu1","kind":"heading","template":"{name}","resolved":true,"html_id":"apdu1","key":"Zi9XNmND9j"}],"key":"aWjWCAF0TI"}],"key":"edbwtaZKya"}],"key":"ZyDCrYO42p"}],"key":"hTpYr6FXJV"},{"type":"heading","depth":3,"position":{"start":{"line":64,"column":1},"end":{"line":64,"column":1}},"children":[{"type":"text","value":"Terminal Key Distribution Station","position":{"start":{"line":64,"column":1},"end":{"line":64,"column":1}},"key":"PlkNnfa9ZR"}],"identifier":"tkd1","label":"tkd1","html_id":"tkd1","key":"h6inLQKISS"},{"type":"paragraph","position":{"start":{"line":66,"column":1},"end":{"line":66,"column":1}},"children":[{"type":"text","value":"Terminal Key Distribution Station e станция, работеща с OS Linux, на която е инсталиран софтуер terminal-kdc и с която е свързан картов четец.","position":{"start":{"line":66,"column":1},"end":{"line":66,"column":1}},"key":"jgQZx6eDRE"}],"key":"ma1KWZVENq"},{"type":"heading","depth":3,"position":{"start":{"line":69,"column":1},"end":{"line":69,"column":1}},"children":[{"type":"text","value":"HSM","position":{"start":{"line":69,"column":1},"end":{"line":69,"column":1}},"key":"QX230aoj4z"}],"identifier":"hsm1","label":"hsm1","html_id":"hsm1","key":"I9iUwH1QSh"},{"type":"paragraph","position":{"start":{"line":71,"column":1},"end":{"line":71,"column":1}},"children":[{"type":"text","value":"HSM е свързан с Terminal Key Distribution Station. Terminal-kdc ползва BDK от HSM.","position":{"start":{"line":71,"column":1},"end":{"line":71,"column":1}},"key":"sgVEtJEVhL"}],"key":"V75DmYT60U"},{"type":"heading","depth":3,"position":{"start":{"line":74,"column":1},"end":{"line":74,"column":1}},"children":[{"type":"text","value":"Картов четец","position":{"start":{"line":74,"column":1},"end":{"line":74,"column":1}},"key":"vv0MHTNC82"}],"identifier":"reader1","label":"reader1","html_id":"reader1","key":"gKuYhn4YsE"},{"type":"paragraph","position":{"start":{"line":76,"column":1},"end":{"line":76,"column":1}},"children":[{"type":"text","value":"Четецът е свързан с Terminal Key Distribution Station и предава данните от terminal-kdc на криптографска смарт карта чрез APDU.","position":{"start":{"line":76,"column":1},"end":{"line":76,"column":1}},"key":"gGbWNb1ts9"}],"key":"efGKrCDRiv"},{"type":"heading","depth":3,"position":{"start":{"line":79,"column":1},"end":{"line":79,"column":1}},"children":[{"type":"text","value":"Терминал","position":{"start":{"line":79,"column":1},"end":{"line":79,"column":1}},"key":"z495P42UVb"}],"identifier":"terminal1","label":"terminal1","html_id":"terminal1","key":"UDuhpM197s"},{"type":"paragraph","position":{"start":{"line":81,"column":1},"end":{"line":81,"column":1}},"children":[{"type":"text","value":"На терминал се зареждат ключовете, които са предварително предназначени конкретно за него. Ключове, които не съдържат данни на съответен терминал, не могат да бъдат заредени.","position":{"start":{"line":81,"column":1},"end":{"line":81,"column":1}},"key":"BO1R5geMxm"}],"key":"AI2cEBPtmi"},{"type":"paragraph","position":{"start":{"line":83,"column":1},"end":{"line":83,"column":1}},"children":[{"type":"text","value":"Трансферът се извършва чрез мобилно приложение Key Transfer Utility, което има роля на крипто смарт карта.","position":{"start":{"line":83,"column":1},"end":{"line":83,"column":1}},"key":"G1BGunZCku"}],"key":"yJDVzB1PY4"},{"type":"heading","depth":3,"position":{"start":{"line":86,"column":1},"end":{"line":86,"column":1}},"children":[{"type":"text","value":"Мобилно устройство","position":{"start":{"line":86,"column":1},"end":{"line":86,"column":1}},"key":"UeRTrKq4ed"}],"identifier":"device1","label":"device1","html_id":"device1","key":"TFMaCuyf42"},{"type":"paragraph","position":{"start":{"line":88,"column":1},"end":{"line":88,"column":1}},"children":[{"type":"text","value":"С цел на осигуряване сигурността на криптографските ключове, в процеса на експорт на TMK и PPK се ползват 2бр. мобилни устройства, на които се качват отделните компоненти на криптографски ключ.","position":{"start":{"line":88,"column":1},"end":{"line":88,"column":1}},"key":"AFPMLbYKfQ"}],"key":"EZWzasYFS5"},{"type":"paragraph","position":{"start":{"line":90,"column":1},"end":{"line":90,"column":1}},"children":[{"type":"text","value":"Мобилните устройства оперират с OS Android.","position":{"start":{"line":90,"column":1},"end":{"line":90,"column":1}},"key":"Jsp9V1Qt1O"}],"key":"rUK216rQif"},{"type":"paragraph","position":{"start":{"line":92,"column":1},"end":{"line":92,"column":1}},"children":[{"type":"text","value":"На мобилните устройства е инсталирано приложение Key Transfer Utility.","position":{"start":{"line":92,"column":1},"end":{"line":92,"column":1}},"key":"G8TzXAw4Yi"}],"key":"heDvFiqMyk"},{"type":"heading","depth":3,"position":{"start":{"line":95,"column":1},"end":{"line":95,"column":1}},"children":[{"type":"text","value":"Key Transfer Utility","position":{"start":{"line":95,"column":1},"end":{"line":95,"column":1}},"key":"DUfAI2h1wc"}],"identifier":"utility1","label":"utility1","html_id":"utility1","key":"D45FEXaCl4"},{"type":"paragraph","position":{"start":{"line":97,"column":1},"end":{"line":97,"column":1}},"children":[{"type":"text","value":"Key Transfer Utility е мобилно приложение, което има роля на криптографскa смарт картa. С негова помощ се осъществява трансфер на криптографски ключове.","position":{"start":{"line":97,"column":1},"end":{"line":97,"column":1}},"key":"XYy4iIn0DT"}],"key":"uSXGhC5ZkI"},{"type":"heading","depth":3,"position":{"start":{"line":100,"column":1},"end":{"line":100,"column":1}},"children":[{"type":"text","value":"Linux","position":{"start":{"line":100,"column":1},"end":{"line":100,"column":1}},"key":"xRxYrMOoWR"}],"identifier":"linux1","label":"linux1","html_id":"linux1","key":"Z5bdm7Meiy"},{"type":"paragraph","position":{"start":{"line":102,"column":1},"end":{"line":102,"column":1}},"children":[{"type":"text","value":"Terminal Key Distribution Station работи с OS Linux.","position":{"start":{"line":102,"column":1},"end":{"line":102,"column":1}},"key":"pqVJIIpyqP"}],"key":"XyvZpt9HTX"},{"type":"paragraph","position":{"start":{"line":104,"column":1},"end":{"line":104,"column":1}},"children":[{"type":"text","value":"OS Linux изисква удостоверяване на потребителя чрез потребителско име и парола.","position":{"start":{"line":104,"column":1},"end":{"line":104,"column":1}},"key":"Oaj1DCy5Ek"}],"key":"zySuTvQ59I"},{"type":"paragraph","position":{"start":{"line":106,"column":1},"end":{"line":106,"column":1}},"children":[{"type":"text","value":"След осъществяване на вход, системата извежда директно интерфейса на terminal-kdc, където следва да се въведат данни на ключ за трансфер.","position":{"start":{"line":106,"column":1},"end":{"line":106,"column":1}},"key":"OXXdG84uzf"}],"key":"K0nzXnaS3y"},{"type":"heading","depth":3,"position":{"start":{"line":109,"column":1},"end":{"line":109,"column":1}},"children":[{"type":"text","value":"Terminal-kdc","position":{"start":{"line":109,"column":1},"end":{"line":109,"column":1}},"key":"lXNjXjX6Pt"}],"identifier":"kdc1","label":"kdc1","html_id":"kdc1","key":"GqfJyY47P9"},{"type":"paragraph","position":{"start":{"line":111,"column":1},"end":{"line":111,"column":1}},"children":[{"type":"text","value":"Terminal-kdc е софтуер, инсталиран на Terminal Key Distribution Station.","position":{"start":{"line":111,"column":1},"end":{"line":111,"column":1}},"key":"jWMeR974uK"}],"key":"hBAwuzAnpS"},{"type":"paragraph","position":{"start":{"line":113,"column":1},"end":{"line":113,"column":1}},"children":[{"type":"text","value":"Чрез terminal-kdc се осъществява зареждане на криптографски ключове, които предстои да бъдат трансферирани на смарт карта.","position":{"start":{"line":113,"column":1},"end":{"line":113,"column":1}},"key":"T7XiJ1ox6V"}],"key":"TwehLs1SZ0"},{"type":"paragraph","position":{"start":{"line":115,"column":1},"end":{"line":115,"column":1}},"children":[{"type":"text","value":"Качване на BDK на Key Distribution Station:","position":{"start":{"line":115,"column":1},"end":{"line":115,"column":1}},"key":"KA33s0nUdW"}],"key":"kLzidQTQkw"},{"type":"list","ordered":false,"spread":false,"position":{"start":{"line":117,"column":1},"end":{"line":121,"column":1}},"children":[{"type":"listItem","spread":true,"position":{"start":{"line":117,"column":1},"end":{"line":117,"column":1}},"children":[{"type":"text","value":"Администратор въвежда ръчно на terminal-kdc етикет на ключ и компоненет 1 и 2 на ключа","position":{"start":{"line":117,"column":1},"end":{"line":117,"column":1}},"key":"KEKQGqbOXU"}],"key":"IWbK0BCYx3"},{"type":"listItem","spread":true,"position":{"start":{"line":118,"column":1},"end":{"line":118,"column":1}},"children":[{"type":"text","value":"изпраща ги на Key Distribution Station","position":{"start":{"line":118,"column":1},"end":{"line":118,"column":1}},"key":"VCaql9pP6K"}],"key":"yjVUSlPsoN"},{"type":"listItem","spread":true,"position":{"start":{"line":119,"column":1},"end":{"line":119,"column":1}},"children":[{"type":"text","value":"Key Distribution Station ги изпраща на HSM заедно с importSecretKey","position":{"start":{"line":119,"column":1},"end":{"line":119,"column":1}},"key":"vsxMz3JXro"}],"key":"XC5oeA7Qgp"},{"type":"listItem","spread":true,"position":{"start":{"line":120,"column":1},"end":{"line":121,"column":1}},"children":[{"type":"text","value":"HSM изпраща BDK на key-distribution-station","position":{"start":{"line":120,"column":1},"end":{"line":120,"column":1}},"key":"sfx6tQBqxl"}],"key":"GhUMM23xSn"}],"key":"X2kfqsrYZr"},{"type":"paragraph","position":{"start":{"line":122,"column":1},"end":{"line":122,"column":1}},"children":[{"type":"text","value":"Трансфер на ключ:","position":{"start":{"line":122,"column":1},"end":{"line":122,"column":1}},"key":"wFl8jT1TXc"}],"key":"c4ywUxf3fu"},{"type":"paragraph","position":{"start":{"line":124,"column":1},"end":{"line":124,"column":1}},"children":[{"type":"text","value":"Чрез terminal-kdc се въвежда:","position":{"start":{"line":124,"column":1},"end":{"line":124,"column":1}},"key":"p195rfjjTo"}],"key":"K3tFrdU4fE"},{"type":"list","ordered":false,"spread":false,"position":{"start":{"line":126,"column":1},"end":{"line":131,"column":1}},"children":[{"type":"listItem","spread":true,"position":{"start":{"line":126,"column":1},"end":{"line":126,"column":1}},"children":[{"type":"text","value":"тип на ключа (TMK, PPK, etc.)","position":{"start":{"line":126,"column":1},"end":{"line":126,"column":1}},"key":"viPq5ZIarj"}],"key":"XYqy0kzlSl"},{"type":"listItem","spread":true,"position":{"start":{"line":127,"column":1},"end":{"line":127,"column":1}},"children":[{"type":"text","value":"идентификационен номер на терминал, за който е предназначен трансфера","position":{"start":{"line":127,"column":1},"end":{"line":127,"column":1}},"key":"upbv5pnhWM"}],"key":"FHIsnucsWU"},{"type":"listItem","spread":true,"position":{"start":{"line":128,"column":1},"end":{"line":131,"column":1}},"children":[{"type":"text","value":"начин на трансфер","position":{"start":{"line":128,"column":1},"end":{"line":128,"column":1}},"key":"oH0WbDtcKf"},{"type":"list","ordered":false,"spread":false,"position":{"start":{"line":129,"column":1},"end":{"line":131,"column":1}},"children":[{"type":"listItem","spread":true,"position":{"start":{"line":129,"column":1},"end":{"line":129,"column":1}},"children":[{"type":"text","value":"TMK: export","position":{"start":{"line":129,"column":1},"end":{"line":129,"column":1}},"key":"d44kSF2cM8"}],"key":"Nn7jMctuK8"},{"type":"listItem","spread":true,"position":{"start":{"line":130,"column":1},"end":{"line":131,"column":1}},"children":[{"type":"text","value":"PPK: export / wrap.","position":{"start":{"line":130,"column":1},"end":{"line":130,"column":1}},"key":"tCY3Sa6ych"}],"key":"Utls57L8HH"}],"key":"h63rxB8AUP"}],"key":"XKJGJELq4u"}],"key":"Ge2TpdXp1a"},{"type":"paragraph","position":{"start":{"line":132,"column":1},"end":{"line":132,"column":1}},"children":[{"type":"text","value":"Процедура export разделя ключа на два компонента, които се трансферират на две различни мобилни устройства с инсталирано приложение Key Transfer Utility.","position":{"start":{"line":132,"column":1},"end":{"line":132,"column":1}},"key":"ebqGW3eGdY"}],"key":"fGxkhLTKk6"},{"type":"heading","depth":3,"position":{"start":{"line":135,"column":1},"end":{"line":135,"column":1}},"children":[{"type":"text","value":"BDK","position":{"start":{"line":135,"column":1},"end":{"line":135,"column":1}},"key":"FvDKybGht1"}],"identifier":"bdk1","label":"bdk1","html_id":"bdk1","key":"sIzaPZRof8"},{"type":"paragraph","position":{"start":{"line":137,"column":1},"end":{"line":137,"column":1}},"children":[{"type":"text","value":"BDK са генерирани на случаен принцип от HSM. Чрез BDK се извеждат всички ключове на терминали.","position":{"start":{"line":137,"column":1},"end":{"line":137,"column":1}},"key":"MDFsTz8H7R"}],"key":"KHhFWZ3frt"},{"type":"heading","depth":3,"position":{"start":{"line":140,"column":1},"end":{"line":140,"column":1}},"children":[{"type":"text","value":"APDU Протокол","position":{"start":{"line":140,"column":1},"end":{"line":140,"column":1}},"key":"WK4wcWzWWi"}],"identifier":"apdu1","label":"apdu1","html_id":"apdu1","key":"c3xp5uHv0K"},{"type":"paragraph","position":{"start":{"line":142,"column":1},"end":{"line":142,"column":1}},"children":[{"type":"text","value":"Application Protocol Data Units (APDU) са команди, които четецът изпраща на смарт картата и съответно чете отговорите от нея.","position":{"start":{"line":142,"column":1},"end":{"line":142,"column":1}},"key":"Krqzw3wrQt"}],"key":"dCI3LUEdwX"},{"type":"paragraph","position":{"start":{"line":144,"column":1},"end":{"line":144,"column":1}},"children":[{"type":"text","value":"APDU се изпраща от четеца към картата, като съдържа задължителен 4-byte header (CLA, INS, P1, P2) и от 0 до 65 535 байта данни. В случаите, когато данните са повече от 256 байта, се прилага допълнително разделяне на фрагменти.","position":{"start":{"line":144,"column":1},"end":{"line":144,"column":1}},"key":"Uxzx1VZUwi"}],"key":"Ez9F4EpOqO"},{"type":"heading","depth":4,"position":{"start":{"line":146,"column":1},"end":{"line":146,"column":1}},"children":[{"type":"text","value":"FCI structure, BER encoded","position":{"start":{"line":146,"column":1},"end":{"line":146,"column":1}},"key":"ikhJheR5RH"}],"identifier":"fci-structure-ber-encoded","label":"FCI structure, BER encoded","html_id":"fci-structure-ber-encoded","implicit":true,"key":"j8hsyI0lmG"},{"type":"table","position":{"start":{"line":148,"column":1},"end":{"line":152,"column":1}},"children":[{"type":"tableRow","position":{"start":{"line":148,"column":1},"end":{"line":148,"column":1}},"children":[{"type":"tableCell","header":true,"position":{"start":{"line":148,"column":1},"end":{"line":148,"column":1}},"children":[{"type":"text","value":"6F NN","position":{"start":{"line":148,"column":1},"end":{"line":148,"column":1}},"key":"Bbi1fUAeMO"}],"key":"TMi2QEek3v"},{"type":"tableCell","header":true,"position":{"start":{"line":148,"column":1},"end":{"line":148,"column":1}},"children":[],"key":"iSU9lOJZqe"}],"key":"p1VUWszNFH"},{"type":"tableRow","position":{"start":{"line":150,"column":1},"end":{"line":150,"column":1}},"children":[{"type":"tableCell","position":{"start":{"line":150,"column":1},"end":{"line":150,"column":1}},"children":[{"type":"text","value":"NN","position":{"start":{"line":150,"column":1},"end":{"line":150,"column":1}},"key":"j1uH1xoFbD"}],"key":"f6ZCI6XgL7"},{"type":"tableCell","position":{"start":{"line":150,"column":1},"end":{"line":150,"column":1}},"children":[{"type":"text","value":"LC (Length of Content)","position":{"start":{"line":150,"column":1},"end":{"line":150,"column":1}},"key":"mJhBY2KyN9"},{"type":"break","key":"hwvgeAkAHP"},{"type":"text","value":"дължината на цялата следваща част:","position":{"start":{"line":150,"column":1},"end":{"line":150,"column":1}},"key":"AM1VkZP9dT"}],"key":"DuLntmFiTO"}],"key":"FHIjw4eTUP"},{"type":"tableRow","position":{"start":{"line":151,"column":1},"end":{"line":151,"column":1}},"children":[{"type":"tableCell","position":{"start":{"line":151,"column":1},"end":{"line":151,"column":1}},"children":[{"type":"text","value":"80 02 VV VV","position":{"start":{"line":151,"column":1},"end":{"line":151,"column":1}},"key":"h4ZRsLb94o"}],"key":"eyTosfiixE"},{"type":"tableCell","position":{"start":{"line":151,"column":1},"end":{"line":151,"column":1}},"children":[{"type":"text","value":"version","position":{"start":{"line":151,"column":1},"end":{"line":151,"column":1}},"key":"XyOt1wCxTU"}],"key":"QBDyTyRgBO"}],"key":"bupL9zstbF"},{"type":"tableRow","position":{"start":{"line":152,"column":1},"end":{"line":152,"column":1}},"children":[{"type":"tableCell","position":{"start":{"line":152,"column":1},"end":{"line":152,"column":1}},"children":[{"type":"text","value":"81 04 BB BB BB BB","position":{"start":{"line":152,"column":1},"end":{"line":152,"column":1}},"key":"AVq5S473GY"}],"key":"b3FVRlH1At"},{"type":"tableCell","position":{"start":{"line":152,"column":1},"end":{"line":152,"column":1}},"children":[{"type":"text","value":"feature and protocol bits","position":{"start":{"line":152,"column":1},"end":{"line":152,"column":1}},"key":"QeZhZMaA55"}],"key":"SM9ZikPCmJ"}],"key":"A8pImhtZwC"}],"key":"sjizcQAkDo"},{"type":"paragraph","position":{"start":{"line":154,"column":1},"end":{"line":154,"column":1}},"children":[{"type":"text","value":"Example:","position":{"start":{"line":154,"column":1},"end":{"line":154,"column":1}},"key":"bMuuou0ZBH"}],"key":"bUxDcliK6J"},{"type":"code","lang":"","value":"  0  10: [APPLICATION 15] {\n  2   2:   [0] 12 34\n  6   4:   [1] FF FF 00 00\n       :   }","position":{"start":{"line":156,"column":1},"end":{"line":161,"column":1}},"key":"u1gWWmQQJO"},{"type":"heading","depth":4,"position":{"start":{"line":163,"column":1},"end":{"line":163,"column":1}},"children":[{"type":"text","value":"PUT DATA Plain Block, BER encoded","position":{"start":{"line":163,"column":1},"end":{"line":163,"column":1}},"key":"gQDe9UXxtA"}],"identifier":"put-data-plain-block-ber-encoded","label":"PUT DATA Plain Block, BER encoded","html_id":"put-data-plain-block-ber-encoded","implicit":true,"key":"IQ2BQxWJZm"},{"type":"table","position":{"start":{"line":165,"column":1},"end":{"line":174,"column":1}},"children":[{"type":"tableRow","position":{"start":{"line":165,"column":1},"end":{"line":165,"column":1}},"children":[{"type":"tableCell","header":true,"position":{"start":{"line":165,"column":1},"end":{"line":165,"column":1}},"children":[{"type":"text","value":"6F NN","position":{"start":{"line":165,"column":1},"end":{"line":165,"column":1}},"key":"uXhTsRRtnh"}],"key":"XsgoC1so3h"},{"type":"tableCell","header":true,"position":{"start":{"line":165,"column":1},"end":{"line":165,"column":1}},"children":[],"key":"XqBA9Qnz41"}],"key":"SkJ3RVLR9F"},{"type":"tableRow","position":{"start":{"line":167,"column":1},"end":{"line":167,"column":1}},"children":[{"type":"tableCell","position":{"start":{"line":167,"column":1},"end":{"line":167,"column":1}},"children":[{"type":"text","value":"NN","position":{"start":{"line":167,"column":1},"end":{"line":167,"column":1}},"key":"lHtXzuISH5"}],"key":"HmcldVSs7h"},{"type":"tableCell","position":{"start":{"line":167,"column":1},"end":{"line":167,"column":1}},"children":[{"type":"text","value":"LC (Length of Content)","position":{"start":{"line":167,"column":1},"end":{"line":167,"column":1}},"key":"tEHeUhHrzH"},{"type":"break","key":"IaMlnu1QJj"},{"type":"text","value":"дължината на цялата следваща част:","position":{"start":{"line":167,"column":1},"end":{"line":167,"column":1}},"key":"TW5VZH2NJy"}],"key":"aJWSn4irKs"}],"key":"nmUB2slJhx"},{"type":"tableRow","position":{"start":{"line":168,"column":1},"end":{"line":168,"column":1}},"children":[{"type":"tableCell","position":{"start":{"line":168,"column":1},"end":{"line":168,"column":1}},"children":[{"type":"text","value":"80 02 XX YY","position":{"start":{"line":168,"column":1},"end":{"line":168,"column":1}},"key":"Oo7qY5YU0a"}],"key":"L4aV89ARzF"},{"type":"tableCell","position":{"start":{"line":168,"column":1},"end":{"line":168,"column":1}},"children":[{"type":"text","value":"02 - размерът на данните от тази част","position":{"start":{"line":168,"column":1},"end":{"line":168,"column":1}},"key":"YqwvkEOFyI"},{"type":"break","key":"IOBnC11LJs"},{"type":"text","value":"XX - block type indicator","position":{"start":{"line":168,"column":1},"end":{"line":168,"column":1}},"key":"J2NtmHQlGF"},{"type":"break","key":"rSUNTzX5rQ"},{"type":"text","value":"YY - control information","position":{"start":{"line":168,"column":1},"end":{"line":168,"column":1}},"key":"wiAUW9ZWwW"},{"type":"break","key":"NA0z68Gyfh"},{"type":"text","value":"първо 00 за ТМК, ","position":{"start":{"line":168,"column":1},"end":{"line":168,"column":1}},"key":"HyvUSBOm2E"},{"type":"break","key":"diQXtz9DXJ"},{"type":"text","value":"0F за PPK, ","position":{"start":{"line":168,"column":1},"end":{"line":168,"column":1}},"key":"FwFpz6SvjE"},{"type":"break","key":"di0KH1KMCC"},{"type":"text","value":"второ 00 за wrap ","position":{"start":{"line":168,"column":1},"end":{"line":168,"column":1}},"key":"Htg6xC9KZG"},{"type":"break","key":"jhrd6ITxac"},{"type":"text","value":"0x02 за експорт на два компонента, първи компонент, ","position":{"start":{"line":168,"column":1},"end":{"line":168,"column":1}},"key":"aTpA7fUWji"},{"type":"break","key":"rVtaVXedno"},{"type":"text","value":"0x12 за втори компонент","position":{"start":{"line":168,"column":1},"end":{"line":168,"column":1}},"key":"eAY32roKX6"}],"key":"kUaBeBcKyM"}],"key":"pZoSCF0dAW"},{"type":"tableRow","position":{"start":{"line":169,"column":1},"end":{"line":169,"column":1}},"children":[{"type":"tableCell","position":{"start":{"line":169,"column":1},"end":{"line":169,"column":1}},"children":[{"type":"text","value":"81 LL AA BB CC ...","position":{"start":{"line":169,"column":1},"end":{"line":169,"column":1}},"key":"bivns3nlWV"}],"key":"losoJC2cTD"},{"type":"tableCell","position":{"start":{"line":169,"column":1},"end":{"line":169,"column":1}},"children":[{"type":"text","value":"target terminal ID","position":{"start":{"line":169,"column":1},"end":{"line":169,"column":1}},"key":"C3pbLNfS82"}],"key":"WawZfuo4te"}],"key":"lqUsuE0LFd"},{"type":"tableRow","position":{"start":{"line":170,"column":1},"end":{"line":170,"column":1}},"children":[{"type":"tableCell","position":{"start":{"line":170,"column":1},"end":{"line":170,"column":1}},"children":[{"type":"text","value":"81 N1 XX XX XX","position":{"start":{"line":170,"column":1},"end":{"line":170,"column":1}},"key":"guT3zWlTYm"}],"key":"MS1jlXaeYY"},{"type":"tableCell","position":{"start":{"line":170,"column":1},"end":{"line":170,"column":1}},"children":[{"type":"text","value":"N1 - размер на ID на терминала","position":{"start":{"line":170,"column":1},"end":{"line":170,"column":1}},"key":"ftvwXAP26y"}],"key":"Qh2Bng23tw"}],"key":"Fd2CxCJvUg"},{"type":"tableRow","position":{"start":{"line":171,"column":1},"end":{"line":171,"column":1}},"children":[{"type":"tableCell","position":{"start":{"line":171,"column":1},"end":{"line":171,"column":1}},"children":[{"type":"text","value":"82 N2 XX XX XX","position":{"start":{"line":171,"column":1},"end":{"line":171,"column":1}},"key":"nTvr9IfRF6"}],"key":"j3GCWhTmXs"},{"type":"tableCell","position":{"start":{"line":171,"column":1},"end":{"line":171,"column":1}},"children":[{"type":"text","value":"N2 - размерът на ключа за пренос","position":{"start":{"line":171,"column":1},"end":{"line":171,"column":1}},"key":"POAXq0kfV8"},{"type":"break","key":"ykTylagOvn"},{"type":"text","value":"Кoгато се извършва експорт на компонент-1 и компонент-2, се слага само една част. Ако са два компонента, те се експортират в две отделни сесии, а обект 80 казва коя част се експортира","position":{"start":{"line":171,"column":1},"end":{"line":171,"column":1}},"key":"AXaYR3djFM"}],"key":"VIqqQEOkxT"}],"key":"iJTOCo4Rlx"},{"type":"tableRow","position":{"start":{"line":172,"column":1},"end":{"line":172,"column":1}},"children":[{"type":"tableCell","position":{"start":{"line":172,"column":1},"end":{"line":172,"column":1}},"children":[{"type":"text","value":"82 10 KK KK KK KK KK KK KK KK KK KK KK KK KK KK KK KK","position":{"start":{"line":172,"column":1},"end":{"line":172,"column":1}},"key":"jV4THUeKUD"}],"key":"YygiIyuSH8"},{"type":"tableCell","position":{"start":{"line":172,"column":1},"end":{"line":172,"column":1}},"children":[{"type":"text","value":"key value / component","position":{"start":{"line":172,"column":1},"end":{"line":172,"column":1}},"key":"GTTA8Cls5S"}],"key":"YXQlnVlv1q"}],"key":"qaTlppdxY8"},{"type":"tableRow","position":{"start":{"line":173,"column":1},"end":{"line":173,"column":1}},"children":[{"type":"tableCell","position":{"start":{"line":173,"column":1},"end":{"line":173,"column":1}},"children":[{"type":"text","value":"83 03 XX XX XX","position":{"start":{"line":173,"column":1},"end":{"line":173,"column":1}},"key":"Xo6S0g6rzE"}],"key":"J6Kx17VL3F"},{"type":"tableCell","position":{"start":{"line":173,"column":1},"end":{"line":173,"column":1}},"children":[{"type":"text","value":"03 - размер на KCV И KCV = XX XX XX","position":{"start":{"line":173,"column":1},"end":{"line":173,"column":1}},"key":"nKOrd73DJp"}],"key":"rtCyhVEfA4"}],"key":"cPM3WqCYmJ"},{"type":"tableRow","position":{"start":{"line":174,"column":1},"end":{"line":174,"column":1}},"children":[{"type":"tableCell","position":{"start":{"line":174,"column":1},"end":{"line":174,"column":1}},"children":[{"type":"text","value":"84 VV VV VV","position":{"start":{"line":174,"column":1},"end":{"line":174,"column":1}},"key":"WjehPDvrPr"}],"key":"ik7A1hm7tY"},{"type":"tableCell","position":{"start":{"line":174,"column":1},"end":{"line":174,"column":1}},"children":[{"type":"text","value":"key check value","position":{"start":{"line":174,"column":1},"end":{"line":174,"column":1}},"key":"NmKfYx1DEu"}],"key":"PuZsVDIh77"}],"key":"naAUfLYX6P"}],"key":"T1OkZjEEjS"},{"type":"paragraph","position":{"start":{"line":176,"column":1},"end":{"line":176,"column":1}},"children":[{"type":"text","value":"Example:","position":{"start":{"line":176,"column":1},"end":{"line":176,"column":1}},"key":"e9oHttzYks"}],"key":"TqmVjzWWEZ"},{"type":"code","lang":"","value":"  0  34: [APPLICATION 10] {\n  2   2:   [0] 00 00\n  6   5:   [1] 12 44 56 78 99\n 13  16:   [2] 44 AB 06 F8 25 5E E6 AC D4 27 04 FD B4 AE A4 08\n 31   3:   [4] AA BB CC\n       :   }","position":{"start":{"line":178,"column":1},"end":{"line":185,"column":1}},"key":"mMnrAdQ17W"},{"type":"heading","depth":2,"position":{"start":{"line":187,"column":1},"end":{"line":187,"column":1}},"children":[{"type":"text","value":"Роли","position":{"start":{"line":187,"column":1},"end":{"line":187,"column":1}},"key":"jwmUpJUXj4"}],"identifier":"id","label":"Роли","html_id":"id-4","implicit":true,"key":"MytXBmyZL8"},{"type":"paragraph","position":{"start":{"line":189,"column":1},"end":{"line":189,"column":1}},"children":[{"type":"text","value":"Роли, права и отговорности по работа със системата са подробно описани в документ ","position":{"start":{"line":189,"column":1},"end":{"line":189,"column":1}},"key":"GyzS9A8Ffa"},{"type":"link","url":"#srs","position":{"start":{"line":189,"column":1},"end":{"line":189,"column":1}},"children":[{"type":"text","value":"System Requirements Specification","position":{"start":{"line":189,"column":1},"end":{"line":189,"column":1}},"key":"gTgWJ32MBy"}],"urlSource":"#srs","key":"VWlcc6SHl0"},{"type":"text","value":".","position":{"start":{"line":189,"column":1},"end":{"line":189,"column":1}},"key":"gYg92yGjQh"}],"key":"pXduXQZMgl"},{"type":"heading","depth":2,"position":{"start":{"line":191,"column":1},"end":{"line":191,"column":1}},"children":[{"type":"text","value":"История на промените","position":{"start":{"line":191,"column":1},"end":{"line":191,"column":1}},"key":"E24lRAXR5R"}],"identifier":"id","label":"История на промените","html_id":"id-5","implicit":true,"key":"WR9SodiIxi"},{"type":"table","position":{"start":{"line":193,"column":1},"end":{"line":196,"column":1}},"children":[{"type":"tableRow","position":{"start":{"line":193,"column":1},"end":{"line":193,"column":1}},"children":[{"type":"tableCell","header":true,"position":{"start":{"line":193,"column":1},"end":{"line":193,"column":1}},"children":[{"type":"text","value":"Версия","position":{"start":{"line":193,"column":1},"end":{"line":193,"column":1}},"key":"v6UpPwc5YP"}],"key":"Pm1pb79Pbm"},{"type":"tableCell","header":true,"position":{"start":{"line":193,"column":1},"end":{"line":193,"column":1}},"children":[{"type":"text","value":"Дата","position":{"start":{"line":193,"column":1},"end":{"line":193,"column":1}},"key":"vQIFu4JA5o"}],"key":"KwAUSx0hsj"},{"type":"tableCell","header":true,"position":{"start":{"line":193,"column":1},"end":{"line":193,"column":1}},"children":[{"type":"text","value":"Описание","position":{"start":{"line":193,"column":1},"end":{"line":193,"column":1}},"key":"xPSSgJBXpm"}],"key":"GmFpWjlcOJ"},{"type":"tableCell","header":true,"position":{"start":{"line":193,"column":1},"end":{"line":193,"column":1}},"children":[{"type":"text","value":"Извършил промяната","position":{"start":{"line":193,"column":1},"end":{"line":193,"column":1}},"key":"dyJWVroGvu"}],"key":"XvtwUUGYrb"}],"key":"qx629rI52c"},{"type":"tableRow","position":{"start":{"line":195,"column":1},"end":{"line":195,"column":1}},"children":[{"type":"tableCell","position":{"start":{"line":195,"column":1},"end":{"line":195,"column":1}},"children":[{"type":"text","value":"1.0","position":{"start":{"line":195,"column":1},"end":{"line":195,"column":1}},"key":"jq0oBKE85Y"}],"key":"akjUEJtCHk"},{"type":"tableCell","position":{"start":{"line":195,"column":1},"end":{"line":195,"column":1}},"children":[{"type":"text","value":"13.01.2023","position":{"start":{"line":195,"column":1},"end":{"line":195,"column":1}},"key":"QMfOlQymkY"}],"key":"nfCYf1RhOK"},{"type":"tableCell","position":{"start":{"line":195,"column":1},"end":{"line":195,"column":1}},"children":[{"type":"text","value":"Начална версия","position":{"start":{"line":195,"column":1},"end":{"line":195,"column":1}},"key":"cdw5qBbUgF"}],"key":"IXhrNYb9uW"},{"type":"tableCell","position":{"start":{"line":195,"column":1},"end":{"line":195,"column":1}},"children":[{"type":"text","value":"Ц. Георгиева","position":{"start":{"line":195,"column":1},"end":{"line":195,"column":1}},"key":"cedph7OpGa"}],"key":"hfv7wFv9uZ"}],"key":"D2xghmwb2S"},{"type":"tableRow","position":{"start":{"line":196,"column":1},"end":{"line":196,"column":1}},"children":[{"type":"tableCell","position":{"start":{"line":196,"column":1},"end":{"line":196,"column":1}},"children":[{"type":"text","value":"1.1","position":{"start":{"line":196,"column":1},"end":{"line":196,"column":1}},"key":"CaWEEtToOw"}],"key":"am5w2muWPf"},{"type":"tableCell","position":{"start":{"line":196,"column":1},"end":{"line":196,"column":1}},"children":[{"type":"text","value":"24.03.2023","position":{"start":{"line":196,"column":1},"end":{"line":196,"column":1}},"key":"MSvGXRDymA"}],"key":"JRsBNeDDSD"},{"type":"tableCell","position":{"start":{"line":196,"column":1},"end":{"line":196,"column":1}},"children":[{"type":"text","value":"Добавено второ мобилно устройство за разделяне двата компонента на крипт. ключ при трансфер","position":{"start":{"line":196,"column":1},"end":{"line":196,"column":1}},"key":"CAEJWrjfBk"}],"key":"N6Ehxhlu9V"},{"type":"tableCell","position":{"start":{"line":196,"column":1},"end":{"line":196,"column":1}},"children":[{"type":"text","value":"Ц. Георгиева","position":{"start":{"line":196,"column":1},"end":{"line":196,"column":1}},"key":"egnu8Yil8U"}],"key":"ffd5y9o1gZ"}],"key":"hKl8Tb5rkI"}],"key":"cPxZDmwg4S"}],"key":"mCrc7tcPCE"}],"key":"UMfaTBUx9h"},"references":{"cite":{"order":[],"data":{}}}}